{
  "success": true,
  "data": {
    "id": "furna-alhara",
    "owner_id": null,
    "business_type_id": "bakery",
    "business_type_name": "مخبز",
    "category_name": "أكل ومطاعم",
    "explore_category": "cat_food",
    "name": "فرن الحارة",
    "name_en": "Hara Bakery",
    "slug": "furna-alhara",
    "handle": "furna-alhara",
    "store_type": "physical",
    "archetype": "menu_order",
    "description": "مخبز عربي تقليدي. خبز عربي، كعك، معجنات طازجة يومياً.",
    "avatar_url": "https://images.unsplash.com/photo-1509440159596-0249088772ff?auto=format&fit=crop&w=200&q=80",
    "cover_url": "https://images.unsplash.com/photo-1517433670267-08bbd4be890f?auto=format&fit=crop&w=800&q=80",
    "phone": "+962790100020",
    "location": {
      "lat": 31.975,
      "lng": 35.860,
      "label": "تلاع العلي، عمّان",
      "area": "تلاع العلي",
      "city": "عمّان"
    },
    "weekly_schedule": {
      "sunday": {"enabled": true, "open": "06:00", "close": "22:00"},
      "monday": {"enabled": true, "open": "06:00", "close": "22:00"},
      "tuesday": {"enabled": true, "open": "06:00", "close": "22:00"},
      "wednesday": {"enabled": true, "open": "06:00", "close": "22:00"},
      "thursday": {"enabled": true, "open": "06:00", "close": "22:00"},
      "friday": {"enabled": true, "open": "06:00", "close": "22:00"},
      "saturday": {"enabled": true, "open": "06:00", "close": "22:00"}
    },
    "operating_hours": "يومياً: ٦:٠٠ ص – ١٠:٠٠ م",
    "items_label_ar": "المنتجات",
    "items_label_en": "Products",
    "is_verified": false,
    "is_open": true,
    "page_status": "active",
    "claim_status": "unclaimed",
    "followers_count": 0,
    "items_count": 0,
    "posts_count": 0,
    "is_following": false,
    "hours": {
      "open_time": "06:00",
      "close_time": "22:00",
      "open_days": ["sunday", "monday", "tuesday", "wednesday", "thursday", "friday", "saturday"]
    },
    "trust_score": 0,
    "trust_metrics": [],
    "delivery_available": false,
    "pickup_available": true,
    "payment_methods": ["نقداً"],
    "member_since": "2023",
    "team_members_count": 0,
    "contact_methods": ["chat", "phone"],
    "created_at": 1640000000,
    "engagement_level": "full",
    "data_synced": false,
    "stories": [],
    "gallery_images": []
  }
}
