{
  "success": true,
  "data": {
    "stats": {
      "received": 1,
      "processing": 1,
      "ready": 1
    },
    "today_summary": {
      "completed": 1,
      "upcoming": 0,
      "cancelled": 0,
      "no_show": 0,
      "total": 4,
      "revenue": 7600
    },
    "live_dropoff": {
      "received": 1,
      "processing": 1,
      "ready": 1,
      "delivered": 1,
      "overdue": 0
    },
    "today_revenue": {
      "total": 7600,
      "yesterday": 6400,
      "completed_count": 2,
      "orders_count": 2,
      "payment_breakdown": {"cash": 4600, "cliq": 2300, "bank": 700},
      "items": [
        { "service": "تفصيل عباية + تقصير بنطلون", "amount": 3300, "time": "10:00" },
        { "service": "تفصيل ثوب", "amount": 2500, "time": "09:00" }
      ]
    },
    "pending_requests": [
      { "id": "req_701", "customer": "سميرة عادل", "service": "تعديل فستان زفاف", "date": "2026-02-14", "time": "10:00" }
    ]
  }
}
